moneytrack/__init__.py
moneytrack/config.py
moneytrack/datasets.py
moneytrack/exceptions.py
moneytrack/moneydata.py
moneytrack/moneyframe.py
moneytrack/moneyframecollection.py
moneytrack/plotting.py
moneytrack/simulation.py
moneytrack/utils.py
moneytrack-0.0.11.data/scripts/build.sh
test/__init__.py
test/test_datasets.py
test/test_moneydata.py
test/test_moneyframe.py
test/test_moneyframecollection.py
test/test_plotting.py
test/test_simulation.py
test/test_utils.py
moneytrack-0.0.11.dist-info/LICENSE
moneytrack-0.0.11.dist-info/METADATA
moneytrack-0.0.11.dist-info/WHEEL
moneytrack-0.0.11.dist-info/top_level.txt
moneytrack-0.0.11.dist-info/RECORD
